lpf2.py
pupremote.py
pupremote-2.1.2.dist-info/licenses/LICENSE.txt
pupremote-2.1.2.dist-info/METADATA
pupremote-2.1.2.dist-info/WHEEL
pupremote-2.1.2.dist-info/top_level.txt
pupremote-2.1.2.dist-info/RECORD
