Metadata-Version: 2.4
Name: pupremote
Version: 2.1.2
Summary: Emulate LEGO Powered Up sensors from MicroPython boards with RPC-style API
Author-email: Anton Vanhoucke & Ste7an <anton@antonsmindstorms.com>
License-Expression: GPL-3.0
Project-URL: Homepage, https://github.com/antonvh/PUPRemote
Project-URL: Repository, https://github.com/antonvh/PUPRemote.git
Project-URL: Documentation, https://github.com/antonvh/PUPRemote
Project-URL: Issues, https://github.com/antonvh/PUPRemote/issues
Keywords: lego,pup,powered-up,sensor,pybricks,micropython,esp32,openmv
Classifier: Development Status :: 5 - Production/Stable
Classifier: Intended Audience :: Developers
Classifier: Intended Audience :: Education
Classifier: Natural Language :: English
Classifier: Operating System :: OS Independent
Classifier: Programming Language :: Python :: Implementation :: MicroPython
Classifier: Topic :: Education
Classifier: Topic :: Software Development :: Libraries :: Python Modules
Classifier: Topic :: System :: Hardware
Requires-Python: >=3.6
License-File: LICENSE.txt
Dynamic: license-file
